odoo_stubs/__init__.py
odoo_stubs/main.py
odoo_stubs-0.1.dev0.dist-info/LICENSE
odoo_stubs-0.1.dev0.dist-info/WHEEL
odoo_stubs-0.1.dev0.dist-info/METADATA
odoo_stubs-0.1.dev0.dist-info/RECORD
