Metadata-Version: 2.1
Name: odoo-stubs
Version: 0.1.dev0
Summary: Project description
Home-page: https://github.com/voronind/odoo-stubs
License: MIT
Author: Dmitry Voronin
Author-email: dmitry665@gmail.com
Requires-Python: >=3.6,<4.0
Classifier: Intended Audience :: Developers
Classifier: License :: OSI Approved :: MIT License
Classifier: Programming Language :: Python :: 3
Classifier: Programming Language :: Python :: 3 :: Only
Classifier: Programming Language :: Python :: 3.6
Classifier: Programming Language :: Python :: 3.7
Classifier: Programming Language :: Python :: 3.8
Classifier: Programming Language :: Python :: 3.9
Classifier: Programming Language :: Python :: Implementation :: PyPy
Classifier: Topic :: Software Development :: Libraries :: Python Modules
Project-URL: Repository, https://github.com/voronind/odoo-stubs
